zipcapture/__init__.py
zipcapture-0.1.dist-info/LICENCE.txt
zipcapture-0.1.dist-info/METADATA
zipcapture-0.1.dist-info/WHEEL
zipcapture-0.1.dist-info/top_level.txt
zipcapture-0.1.dist-info/RECORD
