Metadata-Version: 2.1
Name: zipcapture
Version: 0.1
Summary: Proteus zipcapture File
Home-page: UNKNOWN
Author: Proteus Technology PVT. LTD.
Author-email: <gadgeaniketraghu@gmail.com>
License: UNKNOWN
Keywords: python,first package
Platform: UNKNOWN
Classifier: Development Status :: 3 - Alpha
Classifier: Intended Audience :: Education
Classifier: Programming Language :: Python :: 2
Classifier: Programming Language :: Python :: 3
Classifier: Operating System :: MacOS :: MacOS X
Classifier: Operating System :: Microsoft :: Windows
License-File: LICENCE.txt
Requires-Dist: flask
Requires-Dist: zipcommon
Requires-Dist: imgkit
